django_drf_extensions/__init__.py
django_drf_extensions/cache.py
django_drf_extensions/config.py
django_drf_extensions/mixins.py
django_drf_extensions/processing.py
django_drf_extensions/py.typed
django_drf_extensions/views.py
django_drf_extensions-0.1.68.dist-info/LICENSE
django_drf_extensions-0.1.68.dist-info/METADATA
django_drf_extensions-0.1.68.dist-info/WHEEL
django_drf_extensions-0.1.68.dist-info/RECORD
