Metadata-Version: 2.1
Name: django-drf-extensions
Version: 0.1.68
Summary: Django REST Framework extensions for efficient async and synchronous operations with Celery and Redis
Home-page: https://github.com/AugendLimited/django-drf-extensions
License: MIT
Keywords: django,drf,rest-framework,celery,redis,async,upsert,sync,operations,extensions
Author: Konrad Beck
Author-email: konrad.beck@merchantcapital.co.za
Requires-Python: >=3.11,<4.0
Classifier: Development Status :: 4 - Beta
Classifier: Environment :: Web Environment
Classifier: Framework :: Django
Classifier: Framework :: Django :: 4.0
Classifier: Framework :: Django :: 4.1
Classifier: Framework :: Django :: 4.2
Classifier: Framework :: Django :: 5.0
Classifier: Intended Audience :: Developers
Classifier: License :: OSI Approved :: MIT License
Classifier: Operating System :: OS Independent
Classifier: Programming Language :: Python
Classifier: Programming Language :: Python :: 3
Classifier: Programming Language :: Python :: 3.11
Classifier: Programming Language :: Python :: 3.12
Classifier: Programming Language :: Python :: 3.13
Classifier: Topic :: Internet :: WWW/HTTP
Classifier: Topic :: Software Development :: Libraries :: Python Modules
Requires-Dist: Django (>=4.0,<6.0)
Requires-Dist: celery (>=5.2.0)
Requires-Dist: django-redis (>=5.2.0)
Requires-Dist: djangorestframework (>=3.14.0)
Requires-Dist: redis (>=4.3.0)
Project-URL: Repository, https://github.com/AugendLimited/django-drf-extensions
